nanoasgi.py
NanoASGI-0.0.5.data/scripts/nanoasgi.py
NanoASGI-0.0.5.dist-info/LICENSE
NanoASGI-0.0.5.dist-info/METADATA
NanoASGI-0.0.5.dist-info/WHEEL
NanoASGI-0.0.5.dist-info/top_level.txt
NanoASGI-0.0.5.dist-info/RECORD
