Metadata-Version: 2.1
Name: NanoASGI
Version: 0.0.5
Summary: Fast and simple ASGI-framework for small web-applications.
Home-page: https://nanoasgi.github.io/NanoASGI
Author: Kavindu Santhusa
Author-email: kavindusanthusa@gmail.com
License: MIT
Project-URL: Bug Reports, https://github.com/nanoasgi/NanoASGI/issues
Project-URL: Funding, https://www.buymeacoffee.com/Ksengine
Project-URL: Say Thanks!, https://saythanks.io/to/kavindusanthusa%40gmail.com
Project-URL: Source, https://github.com/nanoasgi/NanoASGI
Keywords: python,asgi,rest,web-framework,fast,simple,lightweight,micro
Platform: any
Classifier: Development Status :: 4 - Beta
Classifier: Operating System :: OS Independent
Classifier: Intended Audience :: Developers
Classifier: License :: OSI Approved :: MIT License
Classifier: Topic :: Internet :: WWW/HTTP
Classifier: Topic :: Internet :: WWW/HTTP :: Dynamic Content :: CGI Tools/Libraries
Classifier: Topic :: Internet :: WWW/HTTP :: HTTP Servers
Classifier: Topic :: Internet :: WWW/HTTP :: WSGI
Classifier: Topic :: Internet :: WWW/HTTP :: WSGI :: Application
Classifier: Topic :: Internet :: WWW/HTTP :: WSGI :: Middleware
Classifier: Topic :: Internet :: WWW/HTTP :: WSGI :: Server
Classifier: Topic :: Software Development :: Libraries :: Application Frameworks
Classifier: Programming Language :: Python :: 3
Classifier: Programming Language :: Python :: 3.6
Classifier: Programming Language :: Python :: 3.7
Classifier: Programming Language :: Python :: 3.8
